{
  "schemaSnapshotVersion": 1,
  "moduleName": "EventManagementModule",
  "databaseProvider": "mssql",
  "generatedAtUtc": "2026-07-22T20:45:42.6086805+00:00",
  "tables": [
    {
      "schema": "dbo",
      "physicalTableName": "AUDIT_LOGS",
      "entityClassStem": "AuditLog",
      "columns": [
        {
          "name": "ACTION",
          "sqlType": "nvarchar(50)",
          "isNullable": false,
          "isPrimaryKey": false,
          "isIdentity": false
        },
        {
          "name": "CHANGED_COLUMNS",
          "sqlType": "nvarchar(max)",
          "isNullable": true,
          "isPrimaryKey": false,
          "isIdentity": false
        },
        {
          "name": "CHANGE_SUMMARY",
          "sqlType": "nvarchar(max)",
          "isNullable": true,
          "isPrimaryKey": false,
          "isIdentity": false
        },
        {
          "name": "CORRELATION_ID",
          "sqlType": "nvarchar(100)",
          "isNullable": true,
          "isPrimaryKey": false,
          "isIdentity": false
        },
        {
          "name": "DURATION_MS",
          "sqlType": "int",
          "isNullable": true,
          "isPrimaryKey": false,
          "isIdentity": false
        },
        {
          "name": "ENTITY_ID",
          "sqlType": "nvarchar(250)",
          "isNullable": false,
          "isPrimaryKey": false,
          "isIdentity": false
        },
        {
          "name": "ENTITY_NAME",
          "sqlType": "nvarchar(250)",
          "isNullable": false,
          "isPrimaryKey": false,
          "isIdentity": false
        },
        {
          "name": "ERROR_MESSAGE",
          "sqlType": "nvarchar(max)",
          "isNullable": true,
          "isPrimaryKey": false,
          "isIdentity": false
        },
        {
          "name": "HASH",
          "sqlType": "nvarchar(128)",
          "isNullable": true,
          "isPrimaryKey": false,
          "isIdentity": false
        },
        {
          "name": "ID",
          "sqlType": "uniqueidentifier",
          "isNullable": false,
          "isPrimaryKey": true,
          "isIdentity": false
        },
        {
          "name": "IP_ADDRESS",
          "sqlType": "nvarchar(50)",
          "isNullable": true,
          "isPrimaryKey": false,
          "isIdentity": false
        },
        {
          "name": "IS_CHANGED",
          "sqlType": "bit",
          "isNullable": true,
          "isPrimaryKey": false,
          "isIdentity": false
        },
        {
          "name": "IS_SUCCESS",
          "sqlType": "bit",
          "isNullable": true,
          "isPrimaryKey": false,
          "isIdentity": false
        },
        {
          "name": "NEW_VALUES",
          "sqlType": "nvarchar(max)",
          "isNullable": true,
          "isPrimaryKey": false,
          "isIdentity": false
        },
        {
          "name": "OLD_VALUES",
          "sqlType": "nvarchar(max)",
          "isNullable": true,
          "isPrimaryKey": false,
          "isIdentity": false
        },
        {
          "name": "REQUEST_MODULE",
          "sqlType": "nvarchar(150)",
          "isNullable": true,
          "isPrimaryKey": false,
          "isIdentity": false
        },
        {
          "name": "REQUEST_PATH",
          "sqlType": "nvarchar(500)",
          "isNullable": true,
          "isPrimaryKey": false,
          "isIdentity": false
        },
        {
          "name": "STATUS_CODE",
          "sqlType": "int",
          "isNullable": true,
          "isPrimaryKey": false,
          "isIdentity": false
        },
        {
          "name": "TIMESTAMP",
          "sqlType": "datetime2(7)",
          "isNullable": false,
          "isPrimaryKey": false,
          "isIdentity": false
        },
        {
          "name": "USER_AGENT",
          "sqlType": "nvarchar(500)",
          "isNullable": true,
          "isPrimaryKey": false,
          "isIdentity": false
        },
        {
          "name": "USER_GROUP",
          "sqlType": "nvarchar(250)",
          "isNullable": true,
          "isPrimaryKey": false,
          "isIdentity": false
        },
        {
          "name": "USER_ID",
          "sqlType": "nvarchar(250)",
          "isNullable": true,
          "isPrimaryKey": false,
          "isIdentity": false
        },
        {
          "name": "USER_NAME",
          "sqlType": "nvarchar(250)",
          "isNullable": true,
          "isPrimaryKey": false,
          "isIdentity": false
        }
      ]
    },
    {
      "schema": "dbo",
      "physicalTableName": "EVENT_ITEMS",
      "entityClassStem": "EventItem",
      "columns": [
        {
          "name": "CREATED_DATE",
          "sqlType": "datetime2(7)",
          "isNullable": false,
          "isPrimaryKey": false,
          "isIdentity": false
        },
        {
          "name": "DESCRIPTION",
          "sqlType": "nvarchar(1000)",
          "isNullable": false,
          "isPrimaryKey": false,
          "isIdentity": false
        },
        {
          "name": "DURATION_MINUTES",
          "sqlType": "int",
          "isNullable": false,
          "isPrimaryKey": false,
          "isIdentity": false
        },
        {
          "name": "EVENT_TYPE",
          "sqlType": "nvarchar(50)",
          "isNullable": false,
          "isPrimaryKey": false,
          "isIdentity": false
        },
        {
          "name": "ID",
          "sqlType": "int",
          "isNullable": false,
          "isPrimaryKey": true,
          "isIdentity": true
        },
        {
          "name": "IS_ACTIVE",
          "sqlType": "bit",
          "isNullable": false,
          "isPrimaryKey": false,
          "isIdentity": false
        },
        {
          "name": "NAME",
          "sqlType": "nvarchar(250)",
          "isNullable": false,
          "isPrimaryKey": false,
          "isIdentity": false
        },
        {
          "name": "POSTER_URL",
          "sqlType": "nvarchar(1000)",
          "isNullable": false,
          "isPrimaryKey": false,
          "isIdentity": false
        },
        {
          "name": "STATUS",
          "sqlType": "nvarchar(50)",
          "isNullable": false,
          "isPrimaryKey": false,
          "isIdentity": false
        },
        {
          "name": "UPDATED_DATE",
          "sqlType": "datetime2(7)",
          "isNullable": false,
          "isPrimaryKey": false,
          "isIdentity": false
        }
      ]
    },
    {
      "schema": "dbo",
      "physicalTableName": "EVENT_TYPES",
      "entityClassStem": "EventType",
      "columns": [
        {
          "name": "DESCRIPTION",
          "sqlType": "nvarchar(250)",
          "isNullable": false,
          "isPrimaryKey": false,
          "isIdentity": false
        },
        {
          "name": "ID",
          "sqlType": "int",
          "isNullable": false,
          "isPrimaryKey": true,
          "isIdentity": true
        },
        {
          "name": "IS_ACTIVE",
          "sqlType": "bit",
          "isNullable": false,
          "isPrimaryKey": false,
          "isIdentity": false
        },
        {
          "name": "TYPE_NAME",
          "sqlType": "nvarchar(50)",
          "isNullable": false,
          "isPrimaryKey": false,
          "isIdentity": false
        }
      ]
    },
    {
      "schema": "dbo",
      "physicalTableName": "SCHEDULES",
      "entityClassStem": "Schedule",
      "columns": [
        {
          "name": "AVAILABLE_SEATS",
          "sqlType": "int",
          "isNullable": false,
          "isPrimaryKey": false,
          "isIdentity": false
        },
        {
          "name": "CREATED_DATE",
          "sqlType": "datetime2(7)",
          "isNullable": false,
          "isPrimaryKey": false,
          "isIdentity": false
        },
        {
          "name": "END_TIME",
          "sqlType": "datetime2(7)",
          "isNullable": false,
          "isPrimaryKey": false,
          "isIdentity": false
        },
        {
          "name": "EVENT_ID",
          "sqlType": "int",
          "isNullable": false,
          "isPrimaryKey": false,
          "isIdentity": false
        },
        {
          "name": "HALL_ID",
          "sqlType": "int",
          "isNullable": false,
          "isPrimaryKey": false,
          "isIdentity": false
        },
        {
          "name": "ID",
          "sqlType": "int",
          "isNullable": false,
          "isPrimaryKey": true,
          "isIdentity": true
        },
        {
          "name": "SCHEDULE_DATE",
          "sqlType": "datetime2(7)",
          "isNullable": false,
          "isPrimaryKey": false,
          "isIdentity": false
        },
        {
          "name": "START_TIME",
          "sqlType": "datetime2(7)",
          "isNullable": false,
          "isPrimaryKey": false,
          "isIdentity": false
        },
        {
          "name": "STATUS",
          "sqlType": "nvarchar(50)",
          "isNullable": false,
          "isPrimaryKey": false,
          "isIdentity": false
        },
        {
          "name": "TOTAL_SEATS",
          "sqlType": "int",
          "isNullable": false,
          "isPrimaryKey": false,
          "isIdentity": false
        },
        {
          "name": "VENUE_ID",
          "sqlType": "int",
          "isNullable": false,
          "isPrimaryKey": false,
          "isIdentity": false
        }
      ]
    },
    {
      "schema": "dbo",
      "physicalTableName": "SCHEDULE_HISTORIES",
      "entityClassStem": "ScheduleHistory",
      "columns": [
        {
          "name": "CHANGED_DATE",
          "sqlType": "datetime2(7)",
          "isNullable": false,
          "isPrimaryKey": false,
          "isIdentity": false
        },
        {
          "name": "CHANGE_REASON",
          "sqlType": "nvarchar(250)",
          "isNullable": false,
          "isPrimaryKey": false,
          "isIdentity": false
        },
        {
          "name": "ID",
          "sqlType": "int",
          "isNullable": false,
          "isPrimaryKey": true,
          "isIdentity": true
        },
        {
          "name": "NEW_STATUS",
          "sqlType": "nvarchar(50)",
          "isNullable": false,
          "isPrimaryKey": false,
          "isIdentity": false
        },
        {
          "name": "PREVIOUS_STATUS",
          "sqlType": "nvarchar(50)",
          "isNullable": false,
          "isPrimaryKey": false,
          "isIdentity": false
        },
        {
          "name": "SCHEDULE_ID",
          "sqlType": "int",
          "isNullable": false,
          "isPrimaryKey": false,
          "isIdentity": false
        }
      ]
    }
  ]
}